mypyliextester/main.py
mypyliextester-22.6.1.post6.dist-info/entry_points.txt
mypyliextester-22.6.1.post6.dist-info/WHEEL
mypyliextester-22.6.1.post6.dist-info/METADATA
mypyliextester-22.6.1.post6.dist-info/RECORD
