Metadata-Version: 2.1
Name: mypyliextester
Version: 22.6.1.post6
Summary: Project description
Home-page: http://github.com/8tm/my_python_library_example_tester
Author: Tadeusz Miszczyk
Author-email: tadeusz.miszczyk@bshg.com
Classifier: Intended Audience :: Developers
Classifier: Operating System :: Unix
Classifier: Programming Language :: Python :: 2
Classifier: Programming Language :: Python :: 2.7
Classifier: Programming Language :: Python :: 3
Classifier: Programming Language :: Python :: 3 :: Only
Classifier: Programming Language :: Python :: 3.10
Classifier: Programming Language :: Python :: 3.4
Classifier: Programming Language :: Python :: 3.5
Classifier: Programming Language :: Python :: 3.6
Classifier: Programming Language :: Python :: 3.7
Classifier: Programming Language :: Python :: 3.8
Classifier: Programming Language :: Python :: 3.9
Requires-Dist: mypyliex (==22.06.01-4)
Project-URL: Documentation, https://test.pypi.org/project/my_python_library_example_tester
Project-URL: Repository, http://github.com/8tm/my_python_library_example_tester
